{
  "StartCities": "Lancer Cities: Skylines II",
  "StopCities": "Arrêter Cities: Skylines II",
  "NoWorkshop": "Désactiver les paquets du Workshop",
  "ExcludeAll": "Retirer tous les éléments de votre playset actif",
  "ExcludeAllDisabled": "Retirer tous les éléments désactivés de votre playset actif",
  "IncludeAll": "Ajouter tous les éléments à votre playset actif",
  "ExcludeAllFiltered": "Retirer les éléments filtrés de votre playset actif",
  "ExcludeAllDisabledFiltered": "Retirer les éléments filtrés et désactivés de votre playset actif",
  "IncludeAllFiltered": "Ajouter les éléments filtrés à votre playset actif",
  "ExcludeAllSelected": "Retirer les éléments sélectionnés de votre playset actif",
  "ExcludeAllDisabledSelected": "Retirer les éléments sélectionnés et désactivés de votre playset actif",
  "IncludeAllSelected": "Ajouter les éléments sélectionnés à votre playset actif",
  "ViewOnWorkshop": "Voir sur PDX Mods",
  "CopyWorkshopLink": {
    "One": "Copier le lien PDX Mods",
    "Plural": "Copier les liens PDX Mods des paquets sélectionnés"
  },
  "CopyWorkshopId": {
    "One": "Copier l'ID PDX Mods",
    "Plural": "Copier les IDs PDX Mods des paquets sélectionnés"
  },
  "LaunchThroughCities": "Lancer avec Cities2.exe",
  "IncludeItem": "Ajouter à votre playset actif",
  "ExcludeItem": "Retirer de votre playset actif",
  "SubscribeToItem": {
    "One": "Ajouter cet élément à votre playset actif",
    "Plural": "Ajouter ces éléments à votre playset actif"
  },
  "IncludeThisItemInAllPlaysets": {
    "One": "Ajouter à tous vos playsets",
    "Plural": "Ajouter les éléments sélectionnés à tous vos playsets"
  },
  "ExcludeThisItemInAllPlaysets": {
    "One": "Retirer de tous vos playsets",
    "Plural": "Retirer les éléments sélectionnés de tous vos playsets"
  },
  "PackageIsRemoved": "\"{0}\" a été supprimé de PDX Mods",
  "PackageIsUnknown": "Les informations de PDX Mods pour \"{0}\" n'ont pas encore chargé",
  "PackageIsIncomplete": "La taille locale de \"{0}\" ({1}) est différente que celle de PDX Mods {2}",
  "OpenCitiesAppData": "Ouvrir le dossier AppData de C:S II",
  "ResetSteamCache": "Vider le cache de PDX Mods",
  "ParadoxLoginFailedTitle": "Could not log you in to PDX Mods",
  "ParadoxLoginFailedNoConnection": "You're not connected to the internet, please check your connection and click here to try again.",
  "ParadoxLoginFailedBadCredentials": "Your saved username/password failed to log in. Click here to update your information.",
  "ParadoxLoginFailedEmpty": "Your session has likely expired. Try launching the game to log in again, or click here to log in through Skyve.",
  "DownloadComplete": "Téléchargement terminé",
  "Downloading": "Téléchargement...",
  "ModDownloadFailed": "Le téléchargement de \"{0}\" a échoué",
  "LoginToParadox": "Log in to Paradox",
  "LoginFailed": "Login failed, make sure your e-mail and password are correct. Or try again later.",
  "RememberMeInfo": "* Your credentials will be encrypted and saved to your computer.",
  "LoginDisclaimer": "The login process is securely handled through Paradox services and no data is shared with Skyve."
}
